CHANGES.md
LICENSE.md
MANIFEST.in
README.md
setup.py
mediawatcher/__init__.py
mediawatcher/__main__.py
mediawatcher/handler.py
mediawatcher/mover.py
mediawatcher.egg-info/PKG-INFO
mediawatcher.egg-info/SOURCES.txt
mediawatcher.egg-info/dependency_links.txt
mediawatcher.egg-info/entry_points.txt
mediawatcher.egg-info/requires.txt
mediawatcher.egg-info/top_level.txt