Metadata-Version: 1.1
Name: mediawatcher
Version: 0.0.3
Summary: Watch directories and move media files accordingly.
Home-page: https://github.com/adrien-f/mediawatcher
Author: Adrien Fillon
Author-email: adrien.fillon+pypi@gmail.com
License: MIT
Keywords: media watcher rename
Platform: UNKNOWN
Classifier: Development Status :: 3 - Alpha
Classifier: Intended Audience :: Developers
Classifier: Topic :: Multimedia
Classifier: License :: OSI Approved :: MIT License
Classifier: Programming Language :: Python :: 3.5
